sbai/__init__.py
sbai/module1.py
sbai-0.1.2.dist-info/LICENSE
sbai-0.1.2.dist-info/METADATA
sbai-0.1.2.dist-info/WHEEL
sbai-0.1.2.dist-info/top_level.txt
sbai-0.1.2.dist-info/RECORD
