Metadata-Version: 2.2
Name: sbai
Version: 0.1.2
Summary: Simplified AI API wrapper for ChatGPT and Google Gemini, enabling easy integration of language models with configurable parameters
Author-email: Shayan Bhutto <py@shayanbhutto.com>
Project-URL: Homepage, https://github.com/shayanbhutto/sbai
Classifier: Programming Language :: Python :: 3
Classifier: License :: OSI Approved :: MIT License
Classifier: Operating System :: OS Independent
Classifier: Intended Audience :: Developers
Classifier: Topic :: Software Development :: Libraries :: Python Modules
Classifier: Topic :: Scientific/Engineering :: Artificial Intelligence
Requires-Python: >=3.8
License-File: LICENSE
Requires-Dist: openai>=1.0
Requires-Dist: google-generativeai>=0.3.0
